{"$id":"1","_raceArmorRenders":[{"$id":"2","_raceNameTag":"Imp","_scriptableRace":"_race/01_race_imp/playerRace_imp","_raceArmorMesh":"_graphic/_mesh/03_item/00_armor/_helm/_hood/helm_hood","_boobOverrideMesh":"","_meshPosition":[0.0,0.0038,-0.0008],"_meshRotation":[6.4,0.0,0.0],"_meshScale":[0.0087,0.0079,0.0086]},{"$id":"3","_raceNameTag":"Poon","_scriptableRace":"_race/02_race_poon/playerRace_poon","_raceArmorMesh":"_graphic/_mesh/03_item/00_armor/_helm/_hood/helm_hood","_boobOverrideMesh":"","_meshPosition":[0.0,0.0054,-0.00035],"_meshRotation":[9.5,0.0,0.0],"_meshScale":[0.0092,0.0087,0.0092]},{"$id":"4","_raceNameTag":"Kubold","_scriptableRace":"_race/03_race_kubold/playerRace_kubold","_raceArmorMesh":"_graphic/_mesh/03_item/00_armor/_helm/_hood/helm_hood","_boobOverrideMesh":"","_meshPosition":[0.0,0.004,-0.0006],"_meshRotation":[11.16,0.0,0.0],"_meshScale":[0.01,0.0083,0.0093]},{"$id":"5","_raceNameTag":"Byrdle","_scriptableRace":"_race/04_race_byrdle/playerRace_byrdle","_raceArmorMesh":"_graphic/_mesh/03_item/00_armor/_helm/_hood/helm_hood","_boobOverrideMesh":"","_meshPosition":[0.0,0.0052,-0.0005],"_meshRotation":[2.17,0.0,0.0],"_meshScale":[0.009,0.009,0.01]},{"$id":"6","_raceNameTag":"Chang","_scriptableRace":"_race/05_race_chang/playerRace_chang","_raceArmorMesh":"_graphic/_mesh/03_item/00_armor/_helm/_hood/helm_hood","_boobOverrideMesh":"","_meshPosition":[0.0,0.0042,-0.0008],"_meshRotation":[14.9,0.0,0.0],"_meshScale":[0.009,0.0082,0.0084]}],"name":"helmRender_hood01","hideFlags":0}